jsgui/__init__.py
jsgui/json_schema_model.py
jsgui/main.py
jsgui/tests/__init__.py
jsgui/tests/test.py
jsgui/view/__init__.py
jsgui/view/tkview.py
jsgui/view/view.py
jsgui-0.9.2.dist-info/METADATA
jsgui-0.9.2.dist-info/WHEEL
jsgui-0.9.2.dist-info/entry_points.txt
jsgui-0.9.2.dist-info/top_level.txt
jsgui-0.9.2.dist-info/RECORD
