Metadata-Version: 2.1
Name: jsgui
Version: 0.9.2
Summary: jsgui provides gui to edit json files based on a schema file
Home-page: https://github.com/truekenji/jsgui
Author: TrueKenji
Keywords: GUI,JSON Schema,JSON,tkinter,decomply,Visualisation
Classifier: Programming Language :: Python :: 3
Classifier: License :: OSI Approved :: MIT License
Classifier: Operating System :: OS Independent
Requires-Dist: numpy
Requires-Dist: jsonschema
Requires-Dist: decomply
